core/__init__.py
core/converter.py
core/preprocessing.py
img2vector-1.2.0.dist-info/licenses/LICENSE
models/__init__.py
models/detector.py
img2vector-1.2.0.dist-info/METADATA
img2vector-1.2.0.dist-info/WHEEL
img2vector-1.2.0.dist-info/entry_points.txt
img2vector-1.2.0.dist-info/top_level.txt
img2vector-1.2.0.dist-info/RECORD
