Metadata-Version: 2.4
Name: img2vector
Version: 1.2.0
Summary: Intelligent image to SVG vectorization with AI-powered optimization
Home-page: https://github.com/sohail000/img2vector
Author: Sohail Khan
Author-email: 2013khansohail@gmail.com
Classifier: Programming Language :: Python :: 3
Classifier: License :: OSI Approved :: MIT License
Classifier: Operating System :: OS Independent
Classifier: Topic :: Multimedia :: Graphics :: Graphics Conversion
Classifier: Topic :: Utilities
Requires-Python: >=3.7
License-File: LICENSE
Requires-Dist: vtracer
Requires-Dist: scikit-image
Requires-Dist: opencv-python
Requires-Dist: numpy
Requires-Dist: pillow
Requires-Dist: gradio>=3.0.0
Requires-Dist: tqdm
Dynamic: author
Dynamic: author-email
Dynamic: classifier
Dynamic: description
Dynamic: description-content-type
Dynamic: home-page
Dynamic: license-file
Dynamic: requires-dist
Dynamic: requires-python
Dynamic: summary
